pydeohub/__init__.py
pydeohub-0.0.1.dist-info/LICENSE
pydeohub-0.0.1.dist-info/METADATA
pydeohub-0.0.1.dist-info/WHEEL
pydeohub-0.0.1.dist-info/top_level.txt
pydeohub-0.0.1.dist-info/RECORD
