Metadata-Version: 2.1
Name: pydeohub
Version: 0.0.1
Summary: Python interface for Blackmagic Design Smart Videohub SDI routers.
Home-page: https://github.com/FlantasticDan/pydeohub
Author: Daniel Flanagan
Project-URL: Bug Tracker, https://github.com/FlantasticDan/pydeohub/issues
Classifier: Programming Language :: Python :: 3
Classifier: License :: OSI Approved :: MIT License
Classifier: Operating System :: OS Independent
Requires-Python: >=3.7
License-File: LICENSE
